{
  "canonical": [
    "screenshots",
    "photos",
    "social",
    "documents",
    "code",
    "data",
    "audio",
    "video",
    "narrative",
    "specs",
    "governance",
    "binary",
    "archive"
  ],
  "aliases": {
    "pdf": "documents",
    "pdfs": "documents",
    "doc": "documents",
    "docs": "documents",
    "document": "documents",
    "text": "documents",
    "txt": "documents",
    "plaintext": "documents",
    "markdown": "documents",
    "md": "documents",
    "files": "documents",
    "file": "documents",
    "textextract": "documents",
    "screenshot": "screenshots",
    "screencapture": "screenshots",
    "screencap": "screenshots",
    "snap": "screenshots",
    "screen": "screenshots",
    "photo": "photos",
    "image": "photos",
    "images": "photos",
    "picture": "photos",
    "pictures": "photos",
    "reddit": "social",
    "redditscreenshots": "social",
    "twitter": "social",
    "instagram": "social",
    "facebook": "social",
    "python": "code",
    "javascript": "code",
    "js": "code",
    "jsx": "code",
    "typescript": "code",
    "ts": "code",
    "bash": "code",
    "batch": "code",
    "script": "code",
    "scripts": "code",
    "source": "code",
    "json": "data",
    "csv": "data",
    "training": "data",
    "dataset": "data",
    "excel": "data",
    "xlsx": "data",
    "m4a": "audio",
    "mp3": "audio",
    "midi": "audio",
    "wav": "audio",
    "mp4": "video",
    "mov": "video",
    "vid": "video",
    "videos": "video",
    "spec": "specs",
    "specification": "specs",
    "unknown": "archive",
    "unsorted": "archive",
    "unidentified": "archive",
    "unread": "archive",
    "misc": "archive",
    "other": "archive"
  },
  "proposed": {}
}
